office_tool/__init__.py
office_tool/office.py
office_tools_mcp_server-0.1.0.dist-info/licenses/LICENSE
office_tools_mcp_server-0.1.0.dist-info/METADATA
office_tools_mcp_server-0.1.0.dist-info/WHEEL
office_tools_mcp_server-0.1.0.dist-info/entry_points.txt
office_tools_mcp_server-0.1.0.dist-info/top_level.txt
office_tools_mcp_server-0.1.0.dist-info/RECORD
