Metadata-Version: 2.4
Name: office-tools-mcp-server
Version: 0.1.0
Summary: Office Tool MCP Server, different types of file could be generated, including PPTs, documents, spreadsheets, webpages and broadcasts.
Requires-Python: >=3.11
License-File: LICENSE
Requires-Dist: aiohttp>=3.11.18
Requires-Dist: fastmcp>=2.4.0
Requires-Dist: python-dotenv>=1.1.0
Requires-Dist: uvicorn>=0.34.2
Dynamic: license-file
